Metadata-Version: 2.1
Name: vsav
Version: 2.0.0
Summary: save, restore, diff files by version.
Home-page: https://github.org/paulwexler/vsav/
Author: Paul Wexler
Author-email: paul.e.wexler@gmail.com
License: MIT
Keywords: save,restore,development
Platform: POSIX
Platform: Linux
Classifier: Development Status :: 5 - Production/Stable
Classifier: Environment :: Console
Classifier: Intended Audience :: Developers
Classifier: License :: OSI Approved :: MIT License
Classifier: Natural Language :: English
Classifier: Operating System :: POSIX :: Linux
Classifier: Programming Language :: Python :: 3
Classifier: Programming Language :: Python :: 3.6
Classifier: Topic :: Software Development
Classifier: Topic :: Utilities
Requires-Python: >=3.6
